py_rust_odbc_csv-1.0.1.dist-info/METADATA
py_rust_odbc_csv-1.0.1.dist-info/WHEEL
py_rust_odbc_csv-1.0.1.dist-info/license_files/LICENSE
py_rust_odbc_csv/__init__.py
py_rust_odbc_csv/py_rust_odbc_csv.cp310-win_amd64.pyd
py_rust_odbc_csv-1.0.1.dist-info/RECORD
