Metadata-Version: 2.1
Name: py-rust-odbc-csv
Version: 1.0.1
Classifier: Programming Language :: Rust
Classifier: Programming Language :: Python :: Implementation :: CPython
Classifier: Programming Language :: Python :: Implementation :: PyPy
License-File: LICENSE
Summary: Python wraper for extracting data from ODBC Source to CSV using Rust, made to be memory eficient and fast!
Author-email: Real Data-Driven <real.datadriven@gmail.com>
Requires-Python: >=3.7
Project-URL: Homepage, https://github.com/realdatadriven/py_rust_odbc_csv
Project-URL: Bug Tracker, https://github.com/realdatadriven/py_rust_odbc_csv/issues
